heymans/__init__.py
heymans/chatbot_model.py
heymans/config.py
heymans/convert.py
heymans/forms.py
heymans/grading_formulas.py
heymans/interactive_quizzes.py
heymans/json_schemas.py
heymans/prompts.py
heymans/quizzes.py
heymans/report.py
heymans/server.py
heymans/database/__init__.py
heymans/database/models.py
heymans/database/schemas.py
heymans/database/operations/__init__.py
heymans/database/operations/documents.py
heymans/database/operations/interactive_quizzes.py
heymans/database/operations/quizzes.py
heymans/database/operations/users.py
heymans/routes/__init__.py
heymans/routes/_app.py
heymans/routes/_documents.py
heymans/routes/_google_login.py
heymans/routes/_interactive_quizzes.py
heymans/routes/_quizzes.py
heymans/routes/_replies.py
heymans/static/Dall-E_heymans.svg
heymans/static/divider.svg
heymans/static/favicon.svg
heymans/static/university-logo--en.svg
heymans/static/css/base.css
heymans/static/css/components.css
heymans/static/css/layout.css
heymans/static/js/common.js
heymans/static/js/vue/quiz.js
heymans/templates/base.html
heymans/templates/example.html
heymans/templates/login.html
heymans/templates/quiz.html
heymans/templates/stylesheet.css
heymans/templates/partials/_quiz_content.html
heymans/templates/partials/banner.html
heymans/templates/partials/footer.html
heymans/templates/partials/head.html
heymans-0.2.4.dist-info/licenses/COPYING
heymans-0.2.4.dist-info/licenses/LICENSE
heymans-0.2.4.dist-info/WHEEL
heymans-0.2.4.dist-info/METADATA
heymans-0.2.4.dist-info/RECORD
