Metadata-Version: 2.4
Name: heymans
Version: 0.2.4
Summary: AI tutor for education
Keywords: ai,chatbot,llm,education
Author-email: Sebastiaan Mathôt <s.mathot@rug.nl>, Wouter Kruijne <w.kruijne@rug.nl>
Requires-Python: >=3.10
License-File: COPYING
License-File: LICENSE
Requires-Dist: sigmund>=1.4.1
Requires-Dist: datamatrix
Requires-Dist: dotenv
Requires-Dist: marshmallow
Requires-Dist: marshmallow-sqlalchemy
Requires-Dist: jsonschema
Requires-Dist: langchain==0.3.27
Requires-Dist: pypandoc
Requires-Dist: matplotlib
Requires-Dist: markdown
Requires-Dist: seaborn
Requires-Dist: numpy
Requires-Dist: scipy
Requires-Dist: pytest ; extra == "test"
Requires-Dist: pytest-cov ; extra == "test"
Project-URL: Source, https://github.com/rug-gmw/heymans
Provides-Extra: test
